alphabetic/__init__.py
alphabetic/core.py
alphabetic/errors.py
alphabetic/data/abjad.json
alphabetic/data/abugida.json
alphabetic/data/alphabet.json
alphabetic/data/featural.json
alphabetic/data/iso_15924_codes.json
alphabetic/data/iso_639_1-2_codes_en_de_fr.json
alphabetic/data/iso_639_3_codes_en.json
alphabetic/data/latin_script_code.json
alphabetic/data/logographic.json
alphabetic/data/syllabary.json
alphabetic-0.0.7.dist-info/METADATA
alphabetic-0.0.7.dist-info/WHEEL
alphabetic-0.0.7.dist-info/licenses/LICENSE
alphabetic-0.0.7.dist-info/RECORD
