Metadata-Version: 2.3
Name: alphabetic
Version: 0.0.7
Summary: A Python module for retrieving script types of writing systems including alphabets, abjads, abugidas, syllabaries, logographs, featurals as well as Latin script codes
Project-URL: Homepage, https://github.com/Halvani/alphabetic
Project-URL: Bug Tracker, https://github.com/Halvani/alphabetic/issues
Author: Oren Halvani
License-File: LICENSE
Keywords: abjads,abugidas,alphabet-characters,alphabet-database,alphabet-list,alphabets,endangered-languages,featural,iso-15924,iso-639-2,iso-639-3,latin-script-codes,logographics,script-types,syllabaries,writing-systems
Classifier: Development Status :: 4 - Beta
Classifier: Intended Audience :: Developers
Classifier: License :: OSI Approved :: MIT License
Classifier: Operating System :: OS Independent
Classifier: Programming Language :: Python :: 3.9
Classifier: Programming Language :: Python :: 3.10
Classifier: Programming Language :: Python :: 3.11
Classifier: Programming Language :: Python :: 3.12
Requires-Python: >=3.9
Requires-Dist: dcl==1.0.0
Requires-Dist: jamo==0.4.1
